__init__.py
main.py
LeonelR033-0.0.1.dist-info/LICENSE
LeonelR033-0.0.1.dist-info/METADATA
LeonelR033-0.0.1.dist-info/WHEEL
LeonelR033-0.0.1.dist-info/top_level.txt
LeonelR033-0.0.1.dist-info/RECORD
