Metadata-Version: 2.1
Name: LeonelR033
Version: 0.0.1
Summary: Kata Range, Coding Dojo in pair plan
Author-email: Leonel Rodríguez - Carlos Rosario <LeonelR03@outlook.com>
License: Copyright (c) 2018 The Python Packaging Authority        
Project-URL: Homepage, https://github.com/LeonelRod/PairDojoKata2.git
Project-URL: Bug Tracker, https://github.com/pypa/sampleproject/issues
Classifier: Programming Language :: Python :: 3
Classifier: License :: OSI Approved :: MIT License
Classifier: Operating System :: OS Independent
Requires-Python: >=3.7
License-File: LICENSE
